lr_cd/__init__.py
lr_cd/lr_cd.py
lr_cd/lr_data_generation.py
lr_cd/lr_plotting.py
lr_cd-0.3.10.dist-info/LICENSE
lr_cd-0.3.10.dist-info/METADATA
lr_cd-0.3.10.dist-info/WHEEL
lr_cd-0.3.10.dist-info/RECORD
