Metadata-Version: 2.1
Name: lr_cd
Version: 0.3.10
Summary: A better implementation of linear regression in Python!
License: MIT
Author: Sam Fo, Jing Wen, Andy Zhang
Requires-Python: >=3.9,<4.0
Classifier: License :: OSI Approved :: MIT License
Classifier: Programming Language :: Python :: 3
Classifier: Programming Language :: Python :: 3.9
Classifier: Programming Language :: Python :: 3.10
Classifier: Programming Language :: Python :: 3.11
Classifier: Programming Language :: Python :: 3.12
Requires-Dist: matplotlib (>=3.8.2,<4.0.0)
Requires-Dist: numpy (>=1.26.3,<2.0.0)
Requires-Dist: pandas (>=2.1.4,<3.0.0)
Requires-Dist: pdflatex (>=0.1.3,<0.2.0)
Requires-Dist: pytest (>=7.4.4,<8.0.0)
Requires-Dist: pytest-cov (>=4.1.0,<5.0.0)
Requires-Dist: scikit-learn (>=1.3.2,<2.0.0)
